nhisml/__init__.py
nhisml/baseline.py
nhisml/evaluate.py
nhisml/explore.py
nhisml/featuresets.py
nhisml/fetch.py
nhisml/nhis_data.py
nhisml/preprocess.py
nhisml/process.py
nhisml/run_srh_prediction.py
nhisml/subgroup.py
nhisml/train.py
nhisml/utils.py
nhisml-0.3.0.dist-info/METADATA
nhisml-0.3.0.dist-info/WHEEL
nhisml-0.3.0.dist-info/entry_points.txt
nhisml-0.3.0.dist-info/top_level.txt
nhisml-0.3.0.dist-info/RECORD
