Metadata-Version: 2.4
Name: nhisml
Version: 0.3.0
Summary: NHIS baseline: fetch Adults 2023/2024 and run SRH prediction
Author-email: JPSM et al <lreign1@umd.edu>
License: MIT
Requires-Python: >=3.9
Requires-Dist: pandas>=2.1
Requires-Dist: pyarrow>=14
Requires-Dist: scikit-learn>=1.4
Requires-Dist: joblib>=1.3
Requires-Dist: requests>=2.31
Requires-Dist: tqdm>=4.66
Requires-Dist: numpy>=1.26
Requires-Dist: duckdb>=1.0
